list_of_us_universities_with_state_code/README.md
list_of_us_universities_with_state_code/__init__.py
list_of_us_universities_with_state_code/main.py
list_of_us_universities_with_state_code/universities_data.json
list_of_us_universities_with_state_code-0.0.2.dist-info/METADATA
list_of_us_universities_with_state_code-0.0.2.dist-info/WHEEL
list_of_us_universities_with_state_code-0.0.2.dist-info/licenses/LICENSE
list_of_us_universities_with_state_code-0.0.2.dist-info/RECORD
