Metadata-Version: 2.3
Name: list_of_us_universities_with_state_code
Version: 0.0.2
Summary: The list of all top US universities along with their state codes, and basic retrieval functions
Project-URL: Homepage, https://github.com/Rajek88/us_universities_with_state_codes
Project-URL: Issues, https://github.com/Rajek88/us_universities_with_state_codes/issues
Author-email: Rajendra Kulkarni <rajerkulkarni@gmail.com>
License-File: LICENSE
Classifier: License :: OSI Approved :: MIT License
Classifier: Operating System :: OS Independent
Classifier: Programming Language :: Python :: 3
Requires-Python: >=3.8
